[
    {
      "id": 1,
      "title": "Nursing Home",
      "price": "FROM $400 WEEKLY",
      "body": "We have dedicated members for nursing elderly people. They don't need to worry about anything.",
      "image": "https://template-kit.rootlayers.com/ecare/wp-content/uploads/sites/23/2021/05/icon8.png"
    },
    {
      "id": 2,
      "title": "Nursing Home",
      "price": "FROM $500 WEEKLY",
      "body": "We have dedicated members for nursing elderly people. They don't need to worry about anything.",
      "image": "https://template-kit.rootlayers.com/ecare/wp-content/uploads/sites/23/2021/05/icon8.png"
    },
    {
      "id": 3,
      "title": "Nursing Home",
      "price": "FROM $400 WEEKLY",
      "body": "We have dedicated members for nursing elderly people. They don't need to worry about anything.",
      "image": "https://template-kit.rootlayers.com/ecare/wp-content/uploads/sites/23/2021/05/icon8.png"
    },
    {
      "id": 4,
      "title": "Nursing Home",
      "price": "FROM $400 WEEKLY",
      "body": "We have dedicated members for nursing elderly people. They don't need to worry about anything.",
      "image": "https://template-kit.rootlayers.com/ecare/wp-content/uploads/sites/23/2021/05/icon8.png"
    },
    {
      "id": 5,
      "title": "Nursing Home",
      "price": "FROM $400 WEEKLY",
      "body": "We have dedicated members for nursing elderly people. They don't need to worry about anything.",
      "image": "https://template-kit.rootlayers.com/ecare/wp-content/uploads/sites/23/2021/05/icon8.png"
    },
    {
      "id": 6,
      "title": "Nursing Home",
      "price": "FROM $900 WEEKLY",
      "body": "We have dedicated members for nursing elderly people. They don't need to worry about anything.",
      "image": "https://template-kit.rootlayers.com/ecare/wp-content/uploads/sites/23/2021/05/icon8.png"
    },
    {
      "id": 7,
      "title": "Nursing Home",
      "price": "FROM $1500 WEEKLY",
      "body": "We have dedicated members for nursing elderly people. They don't need to worry about anything.",
      "image": "https://template-kit.rootlayers.com/ecare/wp-content/uploads/sites/23/2021/05/icon8.png"
    },
    {
      "id": 8,
      "title": "Nursing Home",
      "price": "FROM $1500 WEEKLY",
      "body": "We have dedicated members for nursing elderly people. They don't need to worry about anything.",
      "image": "https://template-kit.rootlayers.com/ecare/wp-content/uploads/sites/23/2021/05/icon8.png"
    },
    {
      "id": 9,
      "title": "Nursing Home",
      "price": "FROM $400 WEEKLY",
      "body": "We have dedicated members for nursing elderly people. They don't need to worry about anything.",
      "image": "https://template-kit.rootlayers.com/ecare/wp-content/uploads/sites/23/2021/05/icon8.png"
    }
  ]